[
    {
      "name": "YouTube",
      "link": "https://www.youtube.com/channel/UCsIIKP2MFRyo8KX3g6358bg",
      "icon": "/Assets/Media/Images/Icons/Youtube.webp"
    },
    {
      "name": "Dribbble",
      "link": "https://dribbble.com/OGLE2003",
      "icon": "Assets/Media/Images/Icons/Social Icons/dribble.png"
    },
    {
      "name": "Facebook",
      "link": "https://www.facebook.com/profile.php?id=61554807376438",
      "icon": "Assets/Media/Images/Icons/Social Icons/Facebook.png"
    },
    {
      "name": "Twitter",
      "link": "https://twitter.com/yourprofile",
      "icon": "/images/social links/Twitter.svg"
    },
    {
      "name": "LinkedIn",
      "link": "https://www.linkedin.com/in/yourprofile",
      "icon": "Assets/Media/Images/Icons/Social Icons/linkedin.png"
    },
    {
      "name": "Instagram",
      "link": "https://www.instagram.com/yourprofile",
      "icon": "Assets/Media/Images/Icons/Social Icons/instagram.png"
    },
    {
      "name": "GitHub",
      "link": "https://github.com/yourprofile",
      "icon": "Assets/Media/Images/Icons/Social Icons/github.png"
    },
    {
      "name": "Pinterest",
      "link": "https://www.pinterest.com/yourprofile",
      "icon": "Assets/Media/Images/Icons/Social Icons/pinterest.png"
    },
    {
      "name": "TikTok",
      "link": "https://www.tiktok.com/@yourprofile",
      "icon": "Assets/Media/Images/Icons/Social Icons/tiktok.png"
    },
    {
      "name": "Reddit",
      "link": "https://www.reddit.com/user/yourprofile",
      "icon": "Assets/Media/Images/Icon.s/Social Icons/reddit.png"
    },
    {
      "name": "Snapchat",
      "link": "https://www.reddit.com/user/yourprofile",
      "icon": "Assets/Media/Images/Icons/Social Icons/snapchat.png"
    },
    {
      "name": "Spotify",
      "link": "https://www.reddit.com/user/yourprofile",
      "icon": "Assets/Media/Images/Icons/Social Icons/spotify.png"
    },
    {
      "name": "Twitter (X)",
      "link": "https://www.reddit.com/user/yourprofile",
      "icon": "Assets/Media/Images/Icons/Social Icons/twitter.png"
    },
    {
      "name": "Twitter (X)",
      "link": "https://www.reddit.com/user/yourprofile",
      "icon": "Assets/Media/Images/Icons/Social Icons/twitter.png"
    },
    {
      "name": "Twitter (X)",
      "link": "https://www.reddit.com/user/yourprofile",
      "icon": "Assets/Media/Images/Icons/Social Icons/twitter.png"
    },
    {
      "name": "Twitter (X)",
      "link": "https://www.reddit.com/user/yourprofile",
      "icon": "Assets/Media/Images/Icons/Social Icons/twitter.png"
    },
    {
      "name": "Twitter (X)",
      "link": "https://www.reddit.com/user/yourprofile",
      "icon": "Assets/Media/Images/Icons/Social Icons/twitter.png"
    },
    {
      "name": "Twitter (X)",
      "link": "https://www.reddit.com/user/yourprofile",
      "icon": "Assets/Media/Images/Icons/Social Icons/twitter.png"
    },
    {
      "name": "Twitter (X)",
      "link": "https://www.reddit.com/user/yourprofile",
      "icon": "Assets/Media/Images/Icons/Social Icons/twitter.png"
    },
    {
      "name": "Twitter (X)",
      "link": "https://www.reddit.com/user/yourprofile",
      "icon": "Assets/Media/Images/Icons/Social Icons/twitter.png"
    },
    {
      "name": "Twitter (X)",
      "link": "https://www.reddit.com/user/yourprofile",
      "icon": "Assets/Media/Images/Icons/Social Icons/twitter.png"
    },
    {
      "name": "Twitter (X)",
      "link": "https://www.reddit.com/user/yourprofile",
      "icon": "Assets/Media/Images/Icons/Social Icons/twitter.png"
    },
    {
      "name": "Twitter (X)",
      "link": "https://www.reddit.com/user/yourprofile",
      "icon": "Assets/Media/Images/Icons/Social Icons/twitter.png"
    },
    {
      "name": "Twitter (X)",
      "link": "https://www.reddit.com/user/yourprofile",
      "icon": "Assets/Media/Images/Icons/Social Icons/twitter.png"
    },
    {
      "name": "Twitter (X)",
      "link": "https://www.reddit.com/user/yourprofile",
      "icon": "Assets/Media/Images/Icons/Social Icons/twitter.png"
    },
    {
      "name": "Twitter (X)",
      "link": "https://www.reddit.com/user/yourprofile",
      "icon": "Assets/Media/Images/Icons/Social Icons/twitter.png"
    },
    {
      "name": "Twitter (X)",
      "link": "https://www.reddit.com/user/yourprofile",
      "icon": "Assets/Media/Images/Icons/Social Icons/twitter.png"
    },
    {
      "name": "Twitter (X)",
      "link": "https://www.reddit.com/user/yourprofile",
      "icon": "Assets/Media/Images/Icons/Social Icons/twitter.png"
    },
    {
      "name": "Twitter (X)",
      "link": "https://www.reddit.com/user/yourprofile",
      "icon": "Assets/Media/Images/Icons/Social Icons/twitter.png"
    },
    {
      "name": "Twitter (X)",
      "link": "https://www.reddit.com/user/yourprofile",
      "icon": "Assets/Media/Images/Icons/Social Icons/twitter.png"
    },
    {
      "name": "Twitter (X)",
      "link": "https://www.reddit.com/user/yourprofile",
      "icon": "Assets/Media/Images/Icons/Social Icons/twitter.png"
    },
    {
      "name": "Twitter (X)",
      "link": "https://www.reddit.com/user/yourprofile",
      "icon": "Assets/Media/Images/Icons/Social Icons/twitter.png"
    },
    {
      "name": "Twitter (X)",
      "link": "https://www.reddit.com/user/yourprofile",
      "icon": "Assets/Media/Images/Icons/Social Icons/twitter.png"
    },
    {
      "name": "Twitter (X)",
      "link": "https://www.reddit.com/user/yourprofile",
      "icon": "Assets/Media/Images/Icons/Social Icons/twitter.png"
    },
    {
      "name": "Twitter (X)",
      "link": "https://www.reddit.com/user/yourprofile",
      "icon": "Assets/Media/Images/Icons/Social Icons/twitter.png"
    },
    {
      "name": "Twitter (X)",
      "link": "https://www.reddit.com/user/yourprofile",
      "icon": "Assets/Media/Images/Icons/Social Icons/twitter.png"
    },
    {
      "name": "Twitter (X)",
      "link": "https://www.reddit.com/user/yourprofile",
      "icon": "Assets/Media/Images/Icons/Social Icons/twitter.png"
    },
    {
      "name": "Twitter (X)",
      "link": "https://www.reddit.com/user/yourprofile",
      "icon": "Assets/Media/Images/Icons/Social Icons/twitter.png"
    },
    {
      "name": "Twitter (X)",
      "link": "https://www.reddit.com/user/yourprofile",
      "icon": "Assets/Media/Images/Icons/Social Icons/twitter.png"
    },
    {
      "name": "Twitter (X)",
      "link": "https://www.reddit.com/user/yourprofile",
      "icon": "Assets/Media/Images/Icons/Social Icons/twitter.png"
    },
    {
      "name": "Twitter (X)",
      "link": "https://www.reddit.com/user/yourprofile",
      "icon": "Assets/Media/Images/Icons/Social Icons/twitter.png"
    },
    {
      "name": "Twitter (X)",
      "link": "https://www.reddit.com/user/yourprofile",
      "icon": "Assets/Media/Images/Icons/Social Icons/twitter.png"
    },
    {
      "name": "Twitter (X)",
      "link": "https://www.reddit.com/user/yourprofile",
      "icon": "Assets/Media/Images/Icons/Social Icons/twitter.png"
    },
    {
      "name": "Twitter (X)",
      "link": "https://www.reddit.com/user/yourprofile",
      "icon": "Assets/Media/Images/Icons/Social Icons/twitter.png"
    },
    {
      "name": "Twitter (X)",
      "link": "https://www.reddit.com/user/yourprofile",
      "icon": "Assets/Media/Images/Icons/Social Icons/twitter.png"
    },
    {
      "name": "Twitter (X)",
      "link": "https://www.reddit.com/user/yourprofile",
      "icon": "Assets/Media/Images/Icons/Social Icons/twitter.png"
    },
    {
      "name": "Twitter (X)",
      "link": "https://www.reddit.com/user/yourprofile",
      "icon": "Assets/Media/Images/Icons/Social Icons/twitter.png"
    },
    {
      "name": "Twitter (X)",
      "link": "https://www.reddit.com/user/yourprofile",
      "icon": "Assets/Media/Images/Icons/Social Icons/twitter.png"
    },
    {
      "name": "Twitter (X)",
      "link": "https://www.reddit.com/user/yourprofile",
      "icon": "Assets/Media/Images/Icons/Social Icons/twitter.png"
    },
    {
      "name": "Twitter (X)",
      "link": "https://www.reddit.com/user/yourprofile",
      "icon": "Assets/Media/Images/Icons/Social Icons/twitter.png"
    },
    {
      "name": "Twitter (X)",
      "link": "https://www.reddit.com/user/yourprofile",
      "icon": "Assets/Media/Images/Icons/Social Icons/twitter.png"
    },
    {
      "name": "Twitter (X)",
      "link": "https://www.reddit.com/user/yourprofile",
      "icon": "Assets/Media/Images/Icons/Social Icons/twitter.png"
    },
    {
      "name": "Twitter (X)",
      "link": "https://www.reddit.com/user/yourprofile",
      "icon": "Assets/Media/Images/Icons/Social Icons/twitter.png"
    },
    {
      "name": "Twitter (X)",
      "link": "https://www.reddit.com/user/yourprofile",
      "icon": "Assets/Media/Images/Icons/Social Icons/twitter.png"
    },
    {
      "name": "Twitter (X)",
      "link": "https://www.reddit.com/user/yourprofile",
      "icon": "Assets/Media/Images/Icons/Social Icons/twitter.png"
    },
    {
      "name": "Twitter (X)",
      "link": "https://www.reddit.com/user/yourprofile",
      "icon": "Assets/Media/Images/Icons/Social Icons/twitter.png"
    },
    {
      "name": "Twitter (X)",
      "link": "https://www.reddit.com/user/yourprofile",
      "icon": "Assets/Media/Images/Icons/Social Icons/twitter.png"
    },
    {
      "name": "Twitter (X)",
      "link": "https://www.reddit.com/user/yourprofile",
      "icon": "Assets/Media/Images/Icons/Social Icons/twitter.png"
    },
    {
      "name": "Twitter (X)",
      "link": "https://www.reddit.com/user/yourprofile",
      "icon": "Assets/Media/Images/Icons/Social Icons/twitter.png"
    },
    {
      "name": "Twitter (X)",
      "link": "https://www.reddit.com/user/yourprofile",
      "icon": "Assets/Media/Images/Icons/Social Icons/twitter.png"
    },
    {
      "name": "Twitter (X)",
      "link": "https://www.reddit.com/user/yourprofile",
      "icon": "Assets/Media/Images/Icons/Social Icons/twitter.png"
    },
    {
      "name": "Twitter (X)",
      "link": "https://www.reddit.com/user/yourprofile",
      "icon": "Assets/Media/Images/Icons/Social Icons/twitter.png"
    },
    {
      "name": "Twitter (X)",
      "link": "https://www.reddit.com/user/yourprofile",
      "icon": "Assets/Media/Images/Icons/Social Icons/twitter.png"
    },
    {
      "name": "Twitter (X)",
      "link": "https://www.reddit.com/user/yourprofile",
      "icon": "Assets/Media/Images/Icons/Social Icons/twitter.png"
    },
    {
      "name": "Twitter (X)",
      "link": "https://www.reddit.com/user/yourprofile",
      "icon": "Assets/Media/Images/Icons/Social Icons/twitter.png"
    },
    {
      "name": "Twitter (X)",
      "link": "https://www.reddit.com/user/yourprofile",
      "icon": "Assets/Media/Images/Icons/Social Icons/twitter.png"
    },
    {
      "name": "Twitter (X)",
      "link": "https://www.reddit.com/user/yourprofile",
      "icon": "Assets/Media/Images/Icons/Social Icons/twitter.png"
    },
    {
      "name": "Twitter (X)",
      "link": "https://www.reddit.com/user/yourprofile",
      "icon": "Assets/Media/Images/Icons/Social Icons/twitter.png"
    },
    {
      "name": "Twitter (X)",
      "link": "https://www.reddit.com/user/yourprofile",
      "icon": "Assets/Media/Images/Icons/Social Icons/twitter.png"
    },
    {
      "name": "Twitter (X)",
      "link": "https://www.reddit.com/user/yourprofile",
      "icon": "Assets/Media/Images/Icons/Social Icons/twitter.png"
    },
    {
      "name": "Twitter (X)",
      "link": "https://www.reddit.com/user/yourprofile",
      "icon": "Assets/Media/Images/Icons/Social Icons/twitter.png"
    },
    {
      "name": "Twitter (X)",
      "link": "https://www.reddit.com/user/yourprofile",
      "icon": "Assets/Media/Images/Icons/Social Icons/twitter.png"
    },
    {
      "name": "Twitter (X)",
      "link": "https://www.reddit.com/user/yourprofile",
      "icon": "Assets/Media/Images/Icons/Social Icons/twitter.png"
    },
    {
      "name": "Twitter (X)",
      "link": "https://www.reddit.com/user/yourprofile",
      "icon": "Assets/Media/Images/Icons/Social Icons/twitter.png"
    },
    {
      "name": "Twitter (X)",
      "link": "https://www.reddit.com/user/yourprofile",
      "icon": "Assets/Media/Images/Icons/Social Icons/twitter.png"
    },
    {
      "name": "Twitter (X)",
      "link": "https://www.reddit.com/user/yourprofile",
      "icon": "Assets/Media/Images/Icons/Social Icons/twitter.png"
    },
    {
      "name": "Twitter (X)",
      "link": "https://www.reddit.com/user/yourprofile",
      "icon": "Assets/Media/Images/Icons/Social Icons/twitter.png"
    },
    {
      "name": "Twitter (X)",
      "link": "https://www.reddit.com/user/yourprofile",
      "icon": "Assets/Media/Images/Icons/Social Icons/twitter.png"
    },
    {
      "name": "Twitter (X)",
      "link": "https://www.reddit.com/user/yourprofile",
      "icon": "Assets/Media/Images/Icons/Social Icons/twitter.png"
    },
    {
      "name": "Twitter (X)",
      "link": "https://www.reddit.com/user/yourprofile",
      "icon": "Assets/Media/Images/Icons/Social Icons/twitter.png"
    },
    {
      "name": "Twitter (X)",
      "link": "https://www.reddit.com/user/yourprofile",
      "icon": "Assets/Media/Images/Icons/Social Icons/twitter.png"
    },
    {
      "name": "Twitter (X)",
      "link": "https://www.reddit.com/user/yourprofile",
      "icon": "Assets/Media/Images/Icons/Social Icons/twitter.png"
    },
    {
      "name": "Twitter (X)",
      "link": "https://www.reddit.com/user/yourprofile",
      "icon": "Assets/Media/Images/Icons/Social Icons/twitter.png"
    },
    {
      "name": "Twitter (X)",
      "link": "https://www.reddit.com/user/yourprofile",
      "icon": "Assets/Media/Images/Icons/Social Icons/twitter.png"
    },
    {
      "name": "Twitter (X)",
      "link": "https://www.reddit.com/user/yourprofile",
      "icon": "Assets/Media/Images/Icons/Social Icons/twitter.png"
    },
    {
      "name": "Twitter (X)",
      "link": "https://www.reddit.com/user/yourprofile",
      "icon": "Assets/Media/Images/Icons/Social Icons/twitter.png"
    },
    {
      "name": "Twitter (X)",
      "link": "https://www.reddit.com/user/yourprofile",
      "icon": "Assets/Media/Images/Icons/Social Icons/twitter.png"
    },
    {
      "name": "Twitter (X)",
      "link": "https://www.reddit.com/user/yourprofile",
      "icon": "Assets/Media/Images/Icons/Social Icons/twitter.png"
    },
    {
      "name": "Twitter (X)",
      "link": "https://www.reddit.com/user/yourprofile",
      "icon": "Assets/Media/Images/Icons/Social Icons/twitter.png"
    },
    {
      "name": "Twitter (X)",
      "link": "https://www.reddit.com/user/yourprofile",
      "icon": "Assets/Media/Images/Icons/Social Icons/twitter.png"
    },
    {
      "name": "Twitter (X)",
      "link": "https://www.reddit.com/user/yourprofile",
      "icon": "Assets/Media/Images/Icons/Social Icons/twitter.png"
    },
    {
      "name": "Twitter (X)",
      "link": "https://www.reddit.com/user/yourprofile",
      "icon": "Assets/Media/Images/Icons/Social Icons/twitter.png"
    },
    {
      "name": "Twitter (X)",
      "link": "https://www.reddit.com/user/yourprofile",
      "icon": "Assets/Media/Images/Icons/Social Icons/twitter.png"
    },
    {
      "name": "Twitter (X)",
      "link": "https://www.reddit.com/user/yourprofile",
      "icon": "Assets/Media/Images/Icons/Social Icons/twitter.png"
    },
    {
      "name": "Twitter (X)",
      "link": "https://www.reddit.com/user/yourprofile",
      "icon": "Assets/Media/Images/Icons/Social Icons/twitter.png"
    },
    {
      "name": "Twitter (X)",
      "link": "https://www.reddit.com/user/yourprofile",
      "icon": "Assets/Media/Images/Icons/Social Icons/twitter.png"
    },
    {
      "name": "Twitter (X)",
      "link": "https://www.reddit.com/user/yourprofile",
      "icon": "Assets/Media/Images/Icons/Social Icons/twitter.png"
    },
    {
      "name": "Twitter (X)",
      "link": "https://www.reddit.com/user/yourprofile",
      "icon": "Assets/Media/Images/Icons/Social Icons/twitter.png"
    },
    {
      "name": "Twitter (X)",
      "link": "https://www.reddit.com/user/yourprofile",
      "icon": "Assets/Media/Images/Icons/Social Icons/twitter.png"
    },
    {
      "name": "Twitter (X)",
      "link": "https://www.reddit.com/user/yourprofile",
      "icon": "Assets/Media/Images/Icons/Social Icons/twitter.png"
    },
    {
      "name": "Twitter (X)",
      "link": "https://www.reddit.com/user/yourprofile",
      "icon": "Assets/Media/Images/Icons/Social Icons/twitter.png"
    },
    {
      "name": "Twitter (X)",
      "link": "https://www.reddit.com/user/yourprofile",
      "icon": "Assets/Media/Images/Icons/Social Icons/twitter.png"
    },
    {
      "name": "Twitter (X)",
      "link": "https://www.reddit.com/user/yourprofile",
      "icon": "Assets/Media/Images/Icons/Social Icons/twitter.png"
    },
    {
      "name": "Twitter (X)",
      "link": "https://www.reddit.com/user/yourprofile",
      "icon": "Assets/Media/Images/Icons/Social Icons/twitter.png"
    },
    {
      "name": "Twitter (X)",
      "link": "https://www.reddit.com/user/yourprofile",
      "icon": "Assets/Media/Images/Icons/Social Icons/twitter.png"
    },
    {
      "name": "Twitter (X)",
      "link": "https://www.reddit.com/user/yourprofile",
      "icon": "Assets/Media/Images/Icons/Social Icons/twitter.png"
    },
    {
      "name": "Twitter (X)",
      "link": "https://www.reddit.com/user/yourprofile",
      "icon": "Assets/Media/Images/Icons/Social Icons/twitter.png"
    },
    {
      "name": "Twitter (X)",
      "link": "https://www.reddit.com/user/yourprofile",
      "icon": "Assets/Media/Images/Icons/Social Icons/twitter.png"
    },
    {
      "name": "Twitter (X)",
      "link": "https://www.reddit.com/user/yourprofile",
      "icon": "Assets/Media/Images/Icons/Social Icons/twitter.png"
    },
    {
      "name": "Twitter (X)",
      "link": "https://www.reddit.com/user/yourprofile",
      "icon": "Assets/Media/Images/Icons/Social Icons/twitter.png"
    },
    {
      "name": "Twitter (X)",
      "link": "https://www.reddit.com/user/yourprofile",
      "icon": "Assets/Media/Images/Icons/Social Icons/twitter.png"
    },
    {
      "name": "Twitter (X)",
      "link": "https://www.reddit.com/user/yourprofile",
      "icon": "Assets/Media/Images/Icons/Social Icons/twitter.png"
    },
    {
      "name": "Twitter (X)",
      "link": "https://www.reddit.com/user/yourprofile",
      "icon": "Assets/Media/Images/Icons/Social Icons/twitter.png"
    },
    {
      "name": "Twitter (X)",
      "link": "https://www.reddit.com/user/yourprofile",
      "icon": "Assets/Media/Images/Icons/Social Icons/twitter.png"
    },
    {
      "name": "Twitter (X)",
      "link": "https://www.reddit.com/user/yourprofile",
      "icon": "Assets/Media/Images/Icons/Social Icons/twitter.png"
    },
    {
      "name": "Twitter (X)",
      "link": "https://www.reddit.com/user/yourprofile",
      "icon": "Assets/Media/Images/Icons/Social Icons/twitter.png"
    },
    {
      "name": "Twitter (X)",
      "link": "https://www.reddit.com/user/yourprofile",
      "icon": "Assets/Media/Images/Icons/Social Icons/twitter.png"
    },
    {
      "name": "Twitter (X)",
      "link": "https://www.reddit.com/user/yourprofile",
      "icon": "Assets/Media/Images/Icons/Social Icons/twitter.png"
    },
    {
      "name": "Twitter (X)",
      "link": "https://www.reddit.com/user/yourprofile",
      "icon": "Assets/Media/Images/Icons/Social Icons/twitter.png"
    },
    {
      "name": "Twitter (X)",
      "link": "https://www.reddit.com/user/yourprofile",
      "icon": "Assets/Media/Images/Icons/Social Icons/twitter.png"
    },
    {
      "name": "Twitter (X)",
      "link": "https://www.reddit.com/user/yourprofile",
      "icon": "Assets/Media/Images/Icons/Social Icons/twitter.png"
    },
    {
      "name": "Twitter (X)",
      "link": "https://www.reddit.com/user/yourprofile",
      "icon": "Assets/Media/Images/Icons/Social Icons/twitter.png"
    },
    {
      "name": "Twitter (X)",
      "link": "https://www.reddit.com/user/yourprofile",
      "icon": "Assets/Media/Images/Icons/Social Icons/twitter.png"
    },
    {
      "name": "Twitter (X)",
      "link": "https://www.reddit.com/user/yourprofile",
      "icon": "Assets/Media/Images/Icons/Social Icons/twitter.png"
    },
    {
      "name": "Twitter (X)",
      "link": "https://www.reddit.com/user/yourprofile",
      "icon": "Assets/Media/Images/Icons/Social Icons/twitter.png"
    },
    {
      "name": "Twitter (X)",
      "link": "https://www.reddit.com/user/yourprofile",
      "icon": "Assets/Media/Images/Icons/Social Icons/twitter.png"
    },
    {
      "name": "Twitter (X)",
      "link": "https://www.reddit.com/user/yourprofile",
      "icon": "Assets/Media/Images/Icons/Social Icons/twitter.png"
    },
    {
      "name": "Twitter (X)",
      "link": "https://www.reddit.com/user/yourprofile",
      "icon": "Assets/Media/Images/Icons/Social Icons/twitter.png"
    },
    {
      "name": "Twitter (X)",
      "link": "https://www.reddit.com/user/yourprofile",
      "icon": "Assets/Media/Images/Icons/Social Icons/twitter.png"
    },
    {
      "name": "Twitter (X)",
      "link": "https://www.reddit.com/user/yourprofile",
      "icon": "Assets/Media/Images/Icons/Social Icons/twitter.png"
    },
    {
      "name": "Twitter (X)",
      "link": "https://www.reddit.com/user/yourprofile",
      "icon": "Assets/Media/Images/Icons/Social Icons/twitter.png"
    },
    {
      "name": "Twitter (X)",
      "link": "https://www.reddit.com/user/yourprofile",
      "icon": "Assets/Media/Images/Icons/Social Icons/twitter.png"
    },
    {
      "name": "Twitter (X)",
      "link": "https://www.reddit.com/user/yourprofile",
      "icon": "Assets/Media/Images/Icons/Social Icons/twitter.png"
    },
    {
      "name": "Twitter (X)",
      "link": "https://www.reddit.com/user/yourprofile",
      "icon": "Assets/Media/Images/Icons/Social Icons/twitter.png"
    },
    {
      "name": "Twitter (X)",
      "link": "https://www.reddit.com/user/yourprofile",
      "icon": "Assets/Media/Images/Icons/Social Icons/twitter.png"
    },
    {
      "name": "Twitter (X)",
      "link": "https://www.reddit.com/user/yourprofile",
      "icon": "Assets/Media/Images/Icons/Social Icons/twitter.png"
    },
    {
      "name": "Twitter (X)",
      "link": "https://www.reddit.com/user/yourprofile",
      "icon": "Assets/Media/Images/Icons/Social Icons/twitter.png"
    },
    {
      "name": "Twitter (X)",
      "link": "https://www.reddit.com/user/yourprofile",
      "icon": "Assets/Media/Images/Icons/Social Icons/twitter.png"
    },
    {
      "name": "Twitter (X)",
      "link": "https://www.reddit.com/user/yourprofile",
      "icon": "Assets/Media/Images/Icons/Social Icons/twitter.png"
    },
    {
      "name": "Twitter (X)",
      "link": "https://www.reddit.com/user/yourprofile",
      "icon": "Assets/Media/Images/Icons/Social Icons/twitter.png"
    },
    {
      "name": "Twitter (X)",
      "link": "https://www.reddit.com/user/yourprofile",
      "icon": "Assets/Media/Images/Icons/Social Icons/twitter.png"
    },
    {
      "name": "Twitter (X)",
      "link": "https://www.reddit.com/user/yourprofile",
      "icon": "Assets/Media/Images/Icons/Social Icons/twitter.png"
    },
    {
      "name": "Twitter (X)",
      "link": "https://www.reddit.com/user/yourprofile",
      "icon": "Assets/Media/Images/Icons/Social Icons/twitter.png"
    },
    {
      "name": "Twitter (X)",
      "link": "https://www.reddit.com/user/yourprofile",
      "icon": "Assets/Media/Images/Icons/Social Icons/twitter.png"
    },
    {
      "name": "Twitter (X)",
      "link": "https://www.reddit.com/user/yourprofile",
      "icon": "Assets/Media/Images/Icons/Social Icons/twitter.png"
    },
    {
      "name": "Twitter (X)",
      "link": "https://www.reddit.com/user/yourprofile",
      "icon": "Assets/Media/Images/Icons/Social Icons/twitter.png"
    },
    {
      "name": "Twitter (X)",
      "link": "https://www.reddit.com/user/yourprofile",
      "icon": "Assets/Media/Images/Icons/Social Icons/twitter.png"
    },
    {
      "name": "Twitter (X)",
      "link": "https://www.reddit.com/user/yourprofile",
      "icon": "Assets/Media/Images/Icons/Social Icons/twitter.png"
    },
    {
      "name": "Twitter (X)",
      "link": "https://www.reddit.com/user/yourprofile",
      "icon": "Assets/Media/Images/Icons/Social Icons/twitter.png"
    },
    {
      "name": "Twitter (X)",
      "link": "https://www.reddit.com/user/yourprofile",
      "icon": "Assets/Media/Images/Icons/Social Icons/twitter.png"
    },
    {
      "name": "Twitter (X)",
      "link": "https://www.reddit.com/user/yourprofile",
      "icon": "Assets/Media/Images/Icons/Social Icons/twitter.png"
    },
    {
      "name": "Twitter (X)",
      "link": "https://www.reddit.com/user/yourprofile",
      "icon": "Assets/Media/Images/Icons/Social Icons/twitter.png"
    },
    {
      "name": "Twitter (X)",
      "link": "https://www.reddit.com/user/yourprofile",
      "icon": "Assets/Media/Images/Icons/Social Icons/twitter.png"
    },
    {
      "name": "Twitter (X)",
      "link": "https://www.reddit.com/user/yourprofile",
      "icon": "Assets/Media/Images/Icons/Social Icons/twitter.png"
    },
    {
      "name": "Twitter (X)",
      "link": "https://www.reddit.com/user/yourprofile",
      "icon": "Assets/Media/Images/Icons/Social Icons/twitter.png"
    },
    {
      "name": "Twitter (X)",
      "link": "https://www.reddit.com/user/yourprofile",
      "icon": "Assets/Media/Images/Icons/Social Icons/twitter.png"
    },
    {
      "name": "Twitter (X)",
      "link": "https://www.reddit.com/user/yourprofile",
      "icon": "Assets/Media/Images/Icons/Social Icons/twitter.png"
    },
    {
      "name": "Twitter (X)",
      "link": "https://www.reddit.com/user/yourprofile",
      "icon": "Assets/Media/Images/Icons/Social Icons/twitter.png"
    },
    {
      "name": "Twitter (X)",
      "link": "https://www.reddit.com/user/yourprofile",
      "icon": "Assets/Media/Images/Icons/Social Icons/twitter.png"
    },
    {
      "name": "Twitter (X)",
      "link": "https://www.reddit.com/user/yourprofile",
      "icon": "Assets/Media/Images/Icons/Social Icons/twitter.png"
    },
    {
      "name": "Twitter (X)",
      "link": "https://www.reddit.com/user/yourprofile",
      "icon": "Assets/Media/Images/Icons/Social Icons/twitter.png"
    },
    {
      "name": "Twitter (X)",
      "link": "https://www.reddit.com/user/yourprofile",
      "icon": "Assets/Media/Images/Icons/Social Icons/twitter.png"
    },
    {
      "name": "Twitter (X)",
      "link": "https://www.reddit.com/user/yourprofile",
      "icon": "Assets/Media/Images/Icons/Social Icons/twitter.png"
    },
    {
      "name": "Twitter (X)",
      "link": "https://www.reddit.com/user/yourprofile",
      "icon": "Assets/Media/Images/Icons/Social Icons/twitter.png"
    },
    {
      "name": "Twitter (X)",
      "link": "https://www.reddit.com/user/yourprofile",
      "icon": "Assets/Media/Images/Icons/Social Icons/twitter.png"
    },
    {
      "name": "Twitter (X)",
      "link": "https://www.reddit.com/user/yourprofile",
      "icon": "Assets/Media/Images/Icons/Social Icons/twitter.png"
    },
    {
      "name": "Twitter (X)",
      "link": "https://www.reddit.com/user/yourprofile",
      "icon": "Assets/Media/Images/Icons/Social Icons/twitter.png"
    },
    {
      "name": "Twitter (X)",
      "link": "https://www.reddit.com/user/yourprofile",
      "icon": "Assets/Media/Images/Icons/Social Icons/twitter.png"
    },
    {
      "name": "Twitter (X)",
      "link": "https://www.reddit.com/user/yourprofile",
      "icon": "Assets/Media/Images/Icons/Social Icons/twitter.png"
    },
    {
      "name": "Twitter (X)",
      "link": "https://www.reddit.com/user/yourprofile",
      "icon": "Assets/Media/Images/Icons/Social Icons/twitter.png"
    },
    {
      "name": "Twitter (X)",
      "link": "https://www.reddit.com/user/yourprofile",
      "icon": "Assets/Media/Images/Icons/Social Icons/twitter.png"
    },
    {
      "name": "Twitter (X)",
      "link": "https://www.reddit.com/user/yourprofile",
      "icon": "Assets/Media/Images/Icons/Social Icons/twitter.png"
    },
    {
      "name": "Twitter (X)",
      "link": "https://www.reddit.com/user/yourprofile",
      "icon": "Assets/Media/Images/Icons/Social Icons/twitter.png"
    },
    {
      "name": "Twitter (X)",
      "link": "https://www.reddit.com/user/yourprofile",
      "icon": "Assets/Media/Images/Icons/Social Icons/twitter.png"
    },
    {
      "name": "Twitter (X)",
      "link": "https://www.reddit.com/user/yourprofile",
      "icon": "Assets/Media/Images/Icons/Social Icons/twitter.png"
    },
    {
      "name": "Twitter (X)",
      "link": "https://www.reddit.com/user/yourprofile",
      "icon": "Assets/Media/Images/Icons/Social Icons/twitter.png"
    },
    {
      "name": "Twitter (X)",
      "link": "https://www.reddit.com/user/yourprofile",
      "icon": "Assets/Media/Images/Icons/Social Icons/twitter.png"
    },
    {
      "name": "Twitter (X)",
      "link": "https://www.reddit.com/user/yourprofile",
      "icon": "Assets/Media/Images/Icons/Social Icons/twitter.png"
    },
    {
      "name": "Twitter (X)",
      "link": "https://www.reddit.com/user/yourprofile",
      "icon": "Assets/Media/Images/Icons/Social Icons/twitter.png"
    },
    {
      "name": "Twitter (X)",
      "link": "https://www.reddit.com/user/yourprofile",
      "icon": "Assets/Media/Images/Icons/Social Icons/twitter.png"
    },
    {
      "name": "Twitter (X)",
      "link": "https://www.reddit.com/user/yourprofile",
      "icon": "Assets/Media/Images/Icons/Social Icons/twitter.png"
    },
    {
      "name": "Twitter (X)",
      "link": "https://www.reddit.com/user/yourprofile",
      "icon": "Assets/Media/Images/Icons/Social Icons/twitter.png"
    },
    {
      "name": "Twitter (X)",
      "link": "https://www.reddit.com/user/yourprofile",
      "icon": "Assets/Media/Images/Icons/Social Icons/twitter.png"
    },
    {
      "name": "Twitter (X)",
      "link": "https://www.reddit.com/user/yourprofile",
      "icon": "Assets/Media/Images/Icons/Social Icons/twitter.png"
    },
    {
      "name": "Twitter (X)",
      "link": "https://www.reddit.com/user/yourprofile",
      "icon": "Assets/Media/Images/Icons/Social Icons/twitter.png"
    },
    {
      "name": "Twitter (X)",
      "link": "https://www.reddit.com/user/yourprofile",
      "icon": "Assets/Media/Images/Icons/Social Icons/twitter.png"
    },
    {
      "name": "Twitter (X)",
      "link": "https://www.reddit.com/user/yourprofile",
      "icon": "Assets/Media/Images/Icons/Social Icons/twitter.png"
    },
    {
      "name": "Twitter (X)",
      "link": "https://www.reddit.com/user/yourprofile",
      "icon": "Assets/Media/Images/Icons/Social Icons/twitter.png"
    },
    {
      "name": "Twitter (X)",
      "link": "https://www.reddit.com/user/yourprofile",
      "icon": "Assets/Media/Images/Icons/Social Icons/twitter.png"
    },
    {
      "name": "Twitter (X)",
      "link": "https://www.reddit.com/user/yourprofile",
      "icon": "Assets/Media/Images/Icons/Social Icons/twitter.png"
    },
    {
      "name": "Twitter (X)",
      "link": "https://www.reddit.com/user/yourprofile",
      "icon": "Assets/Media/Images/Icons/Social Icons/twitter.png"
    },
    {
      "name": "Twitter (X)",
      "link": "https://www.reddit.com/user/yourprofile",
      "icon": "Assets/Media/Images/Icons/Social Icons/twitter.png"
    },
    {
      "name": "Twitter (X)",
      "link": "https://www.reddit.com/user/yourprofile",
      "icon": "Assets/Media/Images/Icons/Social Icons/twitter.png"
    },
    {
      "name": "Twitter (X)",
      "link": "https://www.reddit.com/user/yourprofile",
      "icon": "Assets/Media/Images/Icons/Social Icons/twitter.png"
    },
    {
      "name": "Twitter (X)",
      "link": "https://www.reddit.com/user/yourprofile",
      "icon": "Assets/Media/Images/Icons/Social Icons/twitter.png"
    },
    {
      "name": "Twitter (X)",
      "link": "https://www.reddit.com/user/yourprofile",
      "icon": "Assets/Media/Images/Icons/Social Icons/twitter.png"
    },
    {
      "name": "Twitter (X)",
      "link": "https://www.reddit.com/user/yourprofile",
      "icon": "Assets/Media/Images/Icons/Social Icons/twitter.png"
    },
    {
      "name": "Twitter (X)",
      "link": "https://www.reddit.com/user/yourprofile",
      "icon": "Assets/Media/Images/Icons/Social Icons/twitter.png"
    },
    {
      "name": "Twitter (X)",
      "link": "https://www.reddit.com/user/yourprofile",
      "icon": "Assets/Media/Images/Icons/Social Icons/twitter.png"
    },
    {
      "name": "Twitter (X)",
      "link": "https://www.reddit.com/user/yourprofile",
      "icon": "Assets/Media/Images/Icons/Social Icons/twitter.png"
    },
    {
      "name": "Twitter (X)",
      "link": "https://www.reddit.com/user/yourprofile",
      "icon": "Assets/Media/Images/Icons/Social Icons/twitter.png"
    },
    {
      "name": "Twitter (X)",
      "link": "https://www.reddit.com/user/yourprofile",
      "icon": "Assets/Media/Images/Icons/Social Icons/twitter.png"
    },
    {
      "name": "Twitter (X)",
      "link": "https://www.reddit.com/user/yourprofile",
      "icon": "Assets/Media/Images/Icons/Social Icons/twitter.png"
    },
    {
      "name": "Twitter (X)",
      "link": "https://www.reddit.com/user/yourprofile",
      "icon": "Assets/Media/Images/Icons/Social Icons/twitter.png"
    },
    {
      "name": "Twitter (X)",
      "link": "https://www.reddit.com/user/yourprofile",
      "icon": "Assets/Media/Images/Icons/Social Icons/twitter.png"
    },
    {
      "name": "Twitter (X)",
      "link": "https://www.reddit.com/user/yourprofile",
      "icon": "Assets/Media/Images/Icons/Social Icons/twitter.png"
    },
    {
      "name": "Twitter (X)",
      "link": "https://www.reddit.com/user/yourprofile",
      "icon": "Assets/Media/Images/Icons/Social Icons/twitter.png"
    },
    {
      "name": "Twitter (X)",
      "link": "https://www.reddit.com/user/yourprofile",
      "icon": "Assets/Media/Images/Icons/Social Icons/twitter.png"
    },
    {
      "name": "Twitter (X)",
      "link": "https://www.reddit.com/user/yourprofile",
      "icon": "Assets/Media/Images/Icons/Social Icons/twitter.png"
    },
    {
      "name": "Twitter (X)",
      "link": "https://www.reddit.com/user/yourprofile",
      "icon": "Assets/Media/Images/Icons/Social Icons/twitter.png"
    },
    {
      "name": "Twitter (X)",
      "link": "https://www.reddit.com/user/yourprofile",
      "icon": "Assets/Media/Images/Icons/Social Icons/twitter.png"
    },
    {
      "name": "Twitter (X)",
      "link": "https://www.reddit.com/user/yourprofile",
      "icon": "Assets/Media/Images/Icons/Social Icons/twitter.png"
    },
    {
      "name": "Twitter (X)",
      "link": "https://www.reddit.com/user/yourprofile",
      "icon": "Assets/Media/Images/Icons/Social Icons/twitter.png"
    },
    {
      "name": "Twitter (X)",
      "link": "https://www.reddit.com/user/yourprofile",
      "icon": "Assets/Media/Images/Icons/Social Icons/twitter.png"
    },
    {
      "name": "Twitter (X)",
      "link": "https://www.reddit.com/user/yourprofile",
      "icon": "Assets/Media/Images/Icons/Social Icons/twitter.png"
    },
    {
      "name": "Twitter (X)",
      "link": "https://www.reddit.com/user/yourprofile",
      "icon": "Assets/Media/Images/Icons/Social Icons/twitter.png"
    },
    {
      "name": "Twitter (X)",
      "link": "https://www.reddit.com/user/yourprofile",
      "icon": "Assets/Media/Images/Icons/Social Icons/twitter.png"
    },
    {
      "name": "Twitter (X)",
      "link": "https://www.reddit.com/user/yourprofile",
      "icon": "Assets/Media/Images/Icons/Social Icons/twitter.png"
    },
    {
      "name": "Twitter (X)",
      "link": "https://www.reddit.com/user/yourprofile",
      "icon": "Assets/Media/Images/Icons/Social Icons/twitter.png"
    },
    {
      "name": "Twitter (X)",
      "link": "https://www.reddit.com/user/yourprofile",
      "icon": "Assets/Media/Images/Icons/Social Icons/twitter.png"
    },
    {
      "name": "Twitter (X)",
      "link": "https://www.reddit.com/user/yourprofile",
      "icon": "Assets/Media/Images/Icons/Social Icons/twitter.png"
    },
    {
      "name": "Twitter (X)",
      "link": "https://www.reddit.com/user/yourprofile",
      "icon": "Assets/Media/Images/Icons/Social Icons/twitter.png"
    },
    {
      "name": "Twitter (X)",
      "link": "https://www.reddit.com/user/yourprofile",
      "icon": "Assets/Media/Images/Icons/Social Icons/twitter.png"
    },
    {
      "name": "Twitter (X)",
      "link": "https://www.reddit.com/user/yourprofile",
      "icon": "Assets/Media/Images/Icons/Social Icons/twitter.png"
    },
    {
      "name": "Twitter (X)",
      "link": "https://www.reddit.com/user/yourprofile",
      "icon": "Assets/Media/Images/Icons/Social Icons/twitter.png"
    },
    {
      "name": "Twitter (X)",
      "link": "https://www.reddit.com/user/yourprofile",
      "icon": "Assets/Media/Images/Icons/Social Icons/twitter.png"
    },
    {
      "name": "Twitter (X)",
      "link": "https://www.reddit.com/user/yourprofile",
      "icon": "Assets/Media/Images/Icons/Social Icons/twitter.png"
    },
    {
      "name": "Twitter (X)",
      "link": "https://www.reddit.com/user/yourprofile",
      "icon": "Assets/Media/Images/Icons/Social Icons/twitter.png"
    },
    {
      "name": "Twitter (X)",
      "link": "https://www.reddit.com/user/yourprofile",
      "icon": "Assets/Media/Images/Icons/Social Icons/twitter.png"
    },
    {
      "name": "Twitter (X)",
      "link": "https://www.reddit.com/user/yourprofile",
      "icon": "Assets/Media/Images/Icons/Social Icons/twitter.png"
    },
    {
      "name": "Twitter (X)",
      "link": "https://www.reddit.com/user/yourprofile",
      "icon": "Assets/Media/Images/Icons/Social Icons/twitter.png"
    },
    {
      "name": "Twitter (X)",
      "link": "https://www.reddit.com/user/yourprofile",
      "icon": "Assets/Media/Images/Icons/Social Icons/twitter.png"
    },
    {
      "name": "Twitter (X)",
      "link": "https://www.reddit.com/user/yourprofile",
      "icon": "Assets/Media/Images/Icons/Social Icons/twitter.png"
    },
    {
      "name": "Twitter (X)",
      "link": "https://www.reddit.com/user/yourprofile",
      "icon": "Assets/Media/Images/Icons/Social Icons/twitter.png"
    },
    {
      "name": "Twitter (X)",
      "link": "https://www.reddit.com/user/yourprofile",
      "icon": "Assets/Media/Images/Icons/Social Icons/twitter.png"
    },
    {
      "name": "Twitter (X)",
      "link": "https://www.reddit.com/user/yourprofile",
      "icon": "Assets/Media/Images/Icons/Social Icons/twitter.png"
    },
    {
      "name": "Twitter (X)",
      "link": "https://www.reddit.com/user/yourprofile",
      "icon": "Assets/Media/Images/Icons/Social Icons/twitter.png"
    },
    {
      "name": "Twitter (X)",
      "link": "https://www.reddit.com/user/yourprofile",
      "icon": "Assets/Media/Images/Icons/Social Icons/twitter.png"
    },
    {
      "name": "Twitter (X)",
      "link": "https://www.reddit.com/user/yourprofile",
      "icon": "Assets/Media/Images/Icons/Social Icons/twitter.png"
    },
    {
      "name": "Twitter (X)",
      "link": "https://www.reddit.com/user/yourprofile",
      "icon": "Assets/Media/Images/Icons/Social Icons/twitter.png"
    },
    {
      "name": "Twitter (X)",
      "link": "https://www.reddit.com/user/yourprofile",
      "icon": "Assets/Media/Images/Icons/Social Icons/twitter.png"
    },
    {
      "name": "Twitter (X)",
      "link": "https://www.reddit.com/user/yourprofile",
      "icon": "Assets/Media/Images/Icons/Social Icons/twitter.png"
    },
    {
      "name": "Twitter (X)",
      "link": "https://www.reddit.com/user/yourprofile",
      "icon": "Assets/Media/Images/Icons/Social Icons/twitter.png"
    },
    {
      "name": "Twitter (X)",
      "link": "https://www.reddit.com/user/yourprofile",
      "icon": "Assets/Media/Images/Icons/Social Icons/twitter.png"
    },
    {
      "name": "Twitter (X)",
      "link": "https://www.reddit.com/user/yourprofile",
      "icon": "Assets/Media/Images/Icons/Social Icons/twitter.png"
    },
    {
      "name": "Twitter (X)",
      "link": "https://www.reddit.com/user/yourprofile",
      "icon": "Assets/Media/Images/Icons/Social Icons/twitter.png"
    },
    {
      "name": "Twitter (X)",
      "link": "https://www.reddit.com/user/yourprofile",
      "icon": "Assets/Media/Images/Icons/Social Icons/twitter.png"
    },
    {
      "name": "Twitter (X)",
      "link": "https://www.reddit.com/user/yourprofile",
      "icon": "Assets/Media/Images/Icons/Social Icons/twitter.png"
    },
    {
      "name": "Twitter (X)",
      "link": "https://www.reddit.com/user/yourprofile",
      "icon": "Assets/Media/Images/Icons/Social Icons/twitter.png"
    },
    {
      "name": "Twitter (X)",
      "link": "https://www.reddit.com/user/yourprofile",
      "icon": "Assets/Media/Images/Icons/Social Icons/twitter.png"
    },
    {
      "name": "Twitter (X)",
      "link": "https://www.reddit.com/user/yourprofile",
      "icon": "Assets/Media/Images/Icons/Social Icons/twitter.png"
    },
    {
      "name": "Twitter (X)",
      "link": "https://www.reddit.com/user/yourprofile",
      "icon": "Assets/Media/Images/Icons/Social Icons/twitter.png"
    },
    {
      "name": "Twitter (X)",
      "link": "https://www.reddit.com/user/yourprofile",
      "icon": "Assets/Media/Images/Icons/Social Icons/twitter.png"
    },
    {
      "name": "Twitter (X)",
      "link": "https://www.reddit.com/user/yourprofile",
      "icon": "Assets/Media/Images/Icons/Social Icons/twitter.png"
    },
    {
      "name": "Twitter (X)",
      "link": "https://www.reddit.com/user/yourprofile",
      "icon": "Assets/Media/Images/Icons/Social Icons/twitter.png"
    },
    {
      "name": "Twitter (X)",
      "link": "https://www.reddit.com/user/yourprofile",
      "icon": "Assets/Media/Images/Icons/Social Icons/twitter.png"
    },
    {
      "name": "Twitter (X)",
      "link": "https://www.reddit.com/user/yourprofile",
      "icon": "Assets/Media/Images/Icons/Social Icons/twitter.png"
    },
    {
      "name": "Twitter (X)",
      "link": "https://www.reddit.com/user/yourprofile",
      "icon": "Assets/Media/Images/Icons/Social Icons/twitter.png"
    },
    {
      "name": "Twitter (X)",
      "link": "https://www.reddit.com/user/yourprofile",
      "icon": "Assets/Media/Images/Icons/Social Icons/twitter.png"
    },
    {
      "name": "Twitter (X)",
      "link": "https://www.reddit.com/user/yourprofile",
      "icon": "Assets/Media/Images/Icons/Social Icons/twitter.png"
    },
    {
      "name": "Twitter (X)",
      "link": "https://www.reddit.com/user/yourprofile",
      "icon": "Assets/Media/Images/Icons/Social Icons/twitter.png"
    },
    {
      "name": "Twitter (X)",
      "link": "https://www.reddit.com/user/yourprofile",
      "icon": "Assets/Media/Images/Icons/Social Icons/twitter.png"
    },
    {
      "name": "Twitter (X)",
      "link": "https://www.reddit.com/user/yourprofile",
      "icon": "Assets/Media/Images/Icons/Social Icons/twitter.png"
    },
    {
      "name": "Twitter (X)",
      "link": "https://www.reddit.com/user/yourprofile",
      "icon": "Assets/Media/Images/Icons/Social Icons/twitter.png"
    },
    {
      "name": "Twitter (X)",
      "link": "https://www.reddit.com/user/yourprofile",
      "icon": "Assets/Media/Images/Icons/Social Icons/twitter.png"
    },
    {
      "name": "Twitter (X)",
      "link": "https://www.reddit.com/user/yourprofile",
      "icon": "Assets/Media/Images/Icons/Social Icons/twitter.png"
    },
    {
      "name": "Twitter (X)",
      "link": "https://www.reddit.com/user/yourprofile",
      "icon": "Assets/Media/Images/Icons/Social Icons/twitter.png"
    },
    {
      "name": "Twitter (X)",
      "link": "https://www.reddit.com/user/yourprofile",
      "icon": "Assets/Media/Images/Icons/Social Icons/twitter.png"
    },
    {
      "name": "Twitter (X)",
      "link": "https://www.reddit.com/user/yourprofile",
      "icon": "Assets/Media/Images/Icons/Social Icons/twitter.png"
    },
    {
      "name": "Twitter (X)",
      "link": "https://www.reddit.com/user/yourprofile",
      "icon": "Assets/Media/Images/Icons/Social Icons/twitter.png"
    },
    {
      "name": "Twitter (X)",
      "link": "https://www.reddit.com/user/yourprofile",
      "icon": "Assets/Media/Images/Icons/Social Icons/twitter.png"
    },
    {
      "name": "Twitter (X)",
      "link": "https://www.reddit.com/user/yourprofile",
      "icon": "Assets/Media/Images/Icons/Social Icons/twitter.png"
    },
    {
      "name": "Twitter (X)",
      "link": "https://www.reddit.com/user/yourprofile",
      "icon": "Assets/Media/Images/Icons/Social Icons/twitter.png"
    },
    {
      "name": "Twitter (X)",
      "link": "https://www.reddit.com/user/yourprofile",
      "icon": "Assets/Media/Images/Icons/Social Icons/twitter.png"
    },
    {
      "name": "Twitter (X)",
      "link": "https://www.reddit.com/user/yourprofile",
      "icon": "Assets/Media/Images/Icons/Social Icons/twitter.png"
    },
    {
      "name": "Twitter (X)",
      "link": "https://www.reddit.com/user/yourprofile",
      "icon": "Assets/Media/Images/Icons/Social Icons/twitter.png"
    },
    {
      "name": "Twitter (X)",
      "link": "https://www.reddit.com/user/yourprofile",
      "icon": "Assets/Media/Images/Icons/Social Icons/twitter.png"
    },
    {
      "name": "Twitter (X)",
      "link": "https://www.reddit.com/user/yourprofile",
      "icon": "Assets/Media/Images/Icons/Social Icons/twitter.png"
    },
    {
      "name": "Twitter (X)",
      "link": "https://www.reddit.com/user/yourprofile",
      "icon": "Assets/Media/Images/Icons/Social Icons/twitter.png"
    },
    {
      "name": "Twitter (X)",
      "link": "https://www.reddit.com/user/yourprofile",
      "icon": "Assets/Media/Images/Icons/Social Icons/twitter.png"
    },
    {
      "name": "Twitter (X)",
      "link": "https://www.reddit.com/user/yourprofile",
      "icon": "Assets/Media/Images/Icons/Social Icons/twitter.png"
    },
    {
      "name": "Twitter (X)",
      "link": "https://www.reddit.com/user/yourprofile",
      "icon": "Assets/Media/Images/Icons/Social Icons/twitter.png"
    },
    {
      "name": "Twitter (X)",
      "link": "https://www.reddit.com/user/yourprofile",
      "icon": "Assets/Media/Images/Icons/Social Icons/twitter.png"
    },
    {
      "name": "Twitter (X)",
      "link": "https://www.reddit.com/user/yourprofile",
      "icon": "Assets/Media/Images/Icons/Social Icons/twitter.png"
    },
    {
      "name": "Twitter (X)",
      "link": "https://www.reddit.com/user/yourprofile",
      "icon": "Assets/Media/Images/Icons/Social Icons/twitter.png"
    },
    {
      "name": "Twitter (X)",
      "link": "https://www.reddit.com/user/yourprofile",
      "icon": "Assets/Media/Images/Icons/Social Icons/twitter.png"
    },
    {
      "name": "Twitter (X)",
      "link": "https://www.reddit.com/user/yourprofile",
      "icon": "Assets/Media/Images/Icons/Social Icons/twitter.png"
    },
    {
      "name": "Twitter (X)",
      "link": "https://www.reddit.com/user/yourprofile",
      "icon": "Assets/Media/Images/Icons/Social Icons/twitter.png"
    },
    {
      "name": "Twitter (X)",
      "link": "https://www.reddit.com/user/yourprofile",
      "icon": "Assets/Media/Images/Icons/Social Icons/twitter.png"
    },
    {
      "name": "Twitter (X)",
      "link": "https://www.reddit.com/user/yourprofile",
      "icon": "Assets/Media/Images/Icons/Social Icons/twitter.png"
    },
    {
      "name": "Twitter (X)",
      "link": "https://www.reddit.com/user/yourprofile",
      "icon": "Assets/Media/Images/Icons/Social Icons/twitter.png"
    },
    {
      "name": "Twitter (X)",
      "link": "https://www.reddit.com/user/yourprofile",
      "icon": "Assets/Media/Images/Icons/Social Icons/twitter.png"
    },
    {
      "name": "Twitter (X)",
      "link": "https://www.reddit.com/user/yourprofile",
      "icon": "Assets/Media/Images/Icons/Social Icons/twitter.png"
    },
    {
      "name": "Twitter (X)",
      "link": "https://www.reddit.com/user/yourprofile",
      "icon": "Assets/Media/Images/Icons/Social Icons/twitter.png"
    },
    {
      "name": "Twitter (X)",
      "link": "https://www.reddit.com/user/yourprofile",
      "icon": "Assets/Media/Images/Icons/Social Icons/twitter.png"
    },
    {
      "name": "Twitter (X)",
      "link": "https://www.reddit.com/user/yourprofile",
      "icon": "Assets/Media/Images/Icons/Social Icons/twitter.png"
    },
    {
      "name": "Twitter (X)",
      "link": "https://www.reddit.com/user/yourprofile",
      "icon": "Assets/Media/Images/Icons/Social Icons/twitter.png"
    },
    {
      "name": "Twitter (X)",
      "link": "https://www.reddit.com/user/yourprofile",
      "icon": "Assets/Media/Images/Icons/Social Icons/twitter.png"
    },
    {
      "name": "Twitter (X)",
      "link": "https://www.reddit.com/user/yourprofile",
      "icon": "Assets/Media/Images/Icons/Social Icons/twitter.png"
    },
    {
      "name": "Twitter (X)",
      "link": "https://www.reddit.com/user/yourprofile",
      "icon": "Assets/Media/Images/Icons/Social Icons/twitter.png"
    },
    {
      "name": "Twitter (X)",
      "link": "https://www.reddit.com/user/yourprofile",
      "icon": "Assets/Media/Images/Icons/Social Icons/twitter.png"
    },
    {
      "name": "Twitter (X)",
      "link": "https://www.reddit.com/user/yourprofile",
      "icon": "Assets/Media/Images/Icons/Social Icons/twitter.png"
    },
    {
      "name": "Twitter (X)",
      "link": "https://www.reddit.com/user/yourprofile",
      "icon": "Assets/Media/Images/Icons/Social Icons/twitter.png"
    },
    {
      "name": "Twitter (X)",
      "link": "https://www.reddit.com/user/yourprofile",
      "icon": "Assets/Media/Images/Icons/Social Icons/twitter.png"
    },
    {
      "name": "Twitter (X)",
      "link": "https://www.reddit.com/user/yourprofile",
      "icon": "Assets/Media/Images/Icons/Social Icons/twitter.png"
    },
    {
      "name": "Twitter (X)",
      "link": "https://www.reddit.com/user/yourprofile",
      "icon": "Assets/Media/Images/Icons/Social Icons/twitter.png"
    },
    {
      "name": "Twitter (X)",
      "link": "https://www.reddit.com/user/yourprofile",
      "icon": "Assets/Media/Images/Icons/Social Icons/twitter.png"
    },
    {
      "name": "Twitter (X)",
      "link": "https://www.reddit.com/user/yourprofile",
      "icon": "Assets/Media/Images/Icons/Social Icons/twitter.png"
    },
    {
      "name": "Twitter (X)",
      "link": "https://www.reddit.com/user/yourprofile",
      "icon": "Assets/Media/Images/Icons/Social Icons/twitter.png"
    },
    {
      "name": "Twitter (X)",
      "link": "https://www.reddit.com/user/yourprofile",
      "icon": "Assets/Media/Images/Icons/Social Icons/twitter.png"
    },
    {
      "name": "Twitter (X)",
      "link": "https://www.reddit.com/user/yourprofile",
      "icon": "Assets/Media/Images/Icons/Social Icons/twitter.png"
    },
    {
      "name": "Twitter (X)",
      "link": "https://www.reddit.com/user/yourprofile",
      "icon": "Assets/Media/Images/Icons/Social Icons/twitter.png"
    },
    {
      "name": "Twitter (X)",
      "link": "https://www.reddit.com/user/yourprofile",
      "icon": "Assets/Media/Images/Icons/Social Icons/twitter.png"
    },
    {
      "name": "Twitter (X)",
      "link": "https://www.reddit.com/user/yourprofile",
      "icon": "Assets/Media/Images/Icons/Social Icons/twitter.png"
    },
    {
      "name": "Twitter (X)",
      "link": "https://www.reddit.com/user/yourprofile",
      "icon": "Assets/Media/Images/Icons/Social Icons/twitter.png"
    },
    {
      "name": "Twitter (X)",
      "link": "https://www.reddit.com/user/yourprofile",
      "icon": "Assets/Media/Images/Icons/Social Icons/twitter.png"
    },
    {
      "name": "Twitter (X)",
      "link": "https://www.reddit.com/user/yourprofile",
      "icon": "Assets/Media/Images/Icons/Social Icons/twitter.png"
    },
    {
      "name": "Twitter (X)",
      "link": "https://www.reddit.com/user/yourprofile",
      "icon": "Assets/Media/Images/Icons/Social Icons/twitter.png"
    },
    {
      "name": "Twitter (X)",
      "link": "https://www.reddit.com/user/yourprofile",
      "icon": "Assets/Media/Images/Icons/Social Icons/twitter.png"
    },
    {
      "name": "Twitter (X)",
      "link": "https://www.reddit.com/user/yourprofile",
      "icon": "Assets/Media/Images/Icons/Social Icons/twitter.png"
    },
    {
      "name": "Twitter (X)",
      "link": "https://www.reddit.com/user/yourprofile",
      "icon": "Assets/Media/Images/Icons/Social Icons/twitter.png"
    },
    {
      "name": "Twitter (X)",
      "link": "https://www.reddit.com/user/yourprofile",
      "icon": "Assets/Media/Images/Icons/Social Icons/twitter.png"
    },
    {
      "name": "Twitter (X)",
      "link": "https://www.reddit.com/user/yourprofile",
      "icon": "Assets/Media/Images/Icons/Social Icons/twitter.png"
    },
    {
      "name": "Twitter (X)",
      "link": "https://www.reddit.com/user/yourprofile",
      "icon": "Assets/Media/Images/Icons/Social Icons/twitter.png"
    },
    {
      "name": "Twitter (X)",
      "link": "https://www.reddit.com/user/yourprofile",
      "icon": "Assets/Media/Images/Icons/Social Icons/twitter.png"
    },
    {
      "name": "Twitter (X)",
      "link": "https://www.reddit.com/user/yourprofile",
      "icon": "Assets/Media/Images/Icons/Social Icons/twitter.png"
    },
    {
      "name": "Twitter (X)",
      "link": "https://www.reddit.com/user/yourprofile",
      "icon": "Assets/Media/Images/Icons/Social Icons/twitter.png"
    },
    {
      "name": "Twitter (X)",
      "link": "https://www.reddit.com/user/yourprofile",
      "icon": "Assets/Media/Images/Icons/Social Icons/twitter.png"
    },
    {
      "name": "Twitter (X)",
      "link": "https://www.reddit.com/user/yourprofile",
      "icon": "Assets/Media/Images/Icons/Social Icons/twitter.png"
    },
    {
      "name": "Twitter (X)",
      "link": "https://www.reddit.com/user/yourprofile",
      "icon": "Assets/Media/Images/Icons/Social Icons/twitter.png"
    },
    {
      "name": "Twitter (X)",
      "link": "https://www.reddit.com/user/yourprofile",
      "icon": "Assets/Media/Images/Icons/Social Icons/twitter.png"
    },
    {
      "name": "Twitter (X)",
      "link": "https://www.reddit.com/user/yourprofile",
      "icon": "Assets/Media/Images/Icons/Social Icons/twitter.png"
    },
    {
      "name": "Twitter (X)",
      "link": "https://www.reddit.com/user/yourprofile",
      "icon": "Assets/Media/Images/Icons/Social Icons/twitter.png"
    },
    {
      "name": "Twitter (X)",
      "link": "https://www.reddit.com/user/yourprofile",
      "icon": "Assets/Media/Images/Icons/Social Icons/twitter.png"
    },
    {
      "name": "Twitter (X)",
      "link": "https://www.reddit.com/user/yourprofile",
      "icon": "Assets/Media/Images/Icons/Social Icons/twitter.png"
    },
    {
      "name": "Twitter (X)",
      "link": "https://www.reddit.com/user/yourprofile",
      "icon": "Assets/Media/Images/Icons/Social Icons/twitter.png"
    },
    {
      "name": "Twitter (X)",
      "link": "https://www.reddit.com/user/yourprofile",
      "icon": "Assets/Media/Images/Icons/Social Icons/twitter.png"
    },
    {
      "name": "Twitter (X)",
      "link": "https://www.reddit.com/user/yourprofile",
      "icon": "Assets/Media/Images/Icons/Social Icons/twitter.png"
    },
    {
      "name": "Twitter (X)",
      "link": "https://www.reddit.com/user/yourprofile",
      "icon": "Assets/Media/Images/Icons/Social Icons/twitter.png"
    },
    {
      "name": "Twitter (X)",
      "link": "https://www.reddit.com/user/yourprofile",
      "icon": "Assets/Media/Images/Icons/Social Icons/twitter.png"
    },
    {
      "name": "Twitter (X)",
      "link": "https://www.reddit.com/user/yourprofile",
      "icon": "Assets/Media/Images/Icons/Social Icons/twitter.png"
    },
    {
      "name": "Twitter (X)",
      "link": "https://www.reddit.com/user/yourprofile",
      "icon": "Assets/Media/Images/Icons/Social Icons/twitter.png"
    },
    {
      "name": "Twitter (X)",
      "link": "https://www.reddit.com/user/yourprofile",
      "icon": "Assets/Media/Images/Icons/Social Icons/twitter.png"
    },
    {
      "name": "Twitter (X)",
      "link": "https://www.reddit.com/user/yourprofile",
      "icon": "Assets/Media/Images/Icons/Social Icons/twitter.png"
    },
    {
      "name": "Twitter (X)",
      "link": "https://www.reddit.com/user/yourprofile",
      "icon": "Assets/Media/Images/Icons/Social Icons/twitter.png"
    },
    {
      "name": "Twitter (X)",
      "link": "https://www.reddit.com/user/yourprofile",
      "icon": "Assets/Media/Images/Icons/Social Icons/twitter.png"
    },
    {
      "name": "Twitter (X)",
      "link": "https://www.reddit.com/user/yourprofile",
      "icon": "Assets/Media/Images/Icons/Social Icons/twitter.png"
    },
    {
      "name": "Twitter (X)",
      "link": "https://www.reddit.com/user/yourprofile",
      "icon": "Assets/Media/Images/Icons/Social Icons/twitter.png"
    },
    {
      "name": "Twitter (X)",
      "link": "https://www.reddit.com/user/yourprofile",
      "icon": "Assets/Media/Images/Icons/Social Icons/twitter.png"
    },
    {
      "name": "Twitter (X)",
      "link": "https://www.reddit.com/user/yourprofile",
      "icon": "Assets/Media/Images/Icons/Social Icons/twitter.png"
    },
    {
      "name": "Twitter (X)",
      "link": "https://www.reddit.com/user/yourprofile",
      "icon": "Assets/Media/Images/Icons/Social Icons/twitter.png"
    },
    {
      "name": "Twitter (X)",
      "link": "https://www.reddit.com/user/yourprofile",
      "icon": "Assets/Media/Images/Icons/Social Icons/twitter.png"
    },
    {
      "name": "Twitter (X)",
      "link": "https://www.reddit.com/user/yourprofile",
      "icon": "Assets/Media/Images/Icons/Social Icons/twitter.png"
    },
    {
      "name": "Twitter (X)",
      "link": "https://www.reddit.com/user/yourprofile",
      "icon": "Assets/Media/Images/Icons/Social Icons/twitter.png"
    },
    {
      "name": "Twitter (X)",
      "link": "https://www.reddit.com/user/yourprofile",
      "icon": "Assets/Media/Images/Icons/Social Icons/twitter.png"
    },
    {
      "name": "Twitter (X)",
      "link": "https://www.reddit.com/user/yourprofile",
      "icon": "Assets/Media/Images/Icons/Social Icons/twitter.png"
    },
    {
      "name": "Twitter (X)",
      "link": "https://www.reddit.com/user/yourprofile",
      "icon": "Assets/Media/Images/Icons/Social Icons/twitter.png"
    },
    {
      "name": "Twitter (X)",
      "link": "https://www.reddit.com/user/yourprofile",
      "icon": "Assets/Media/Images/Icons/Social Icons/twitter.png"
    },
    {
      "name": "Twitter (X)",
      "link": "https://www.reddit.com/user/yourprofile",
      "icon": "Assets/Media/Images/Icons/Social Icons/twitter.png"
    },
    {
      "name": "Twitter (X)",
      "link": "https://www.reddit.com/user/yourprofile",
      "icon": "Assets/Media/Images/Icons/Social Icons/twitter.png"
    },
    {
      "name": "Twitter (X)",
      "link": "https://www.reddit.com/user/yourprofile",
      "icon": "Assets/Media/Images/Icons/Social Icons/twitter.png"
    },
    {
      "name": "Twitter (X)",
      "link": "https://www.reddit.com/user/yourprofile",
      "icon": "Assets/Media/Images/Icons/Social Icons/twitter.png"
    }
]